setup.py
prygress/__init__.py
prygress/prygress.py
prygress.egg-info/PKG-INFO
prygress.egg-info/SOURCES.txt
prygress.egg-info/dependency_links.txt
prygress.egg-info/not-zip-safe
prygress.egg-info/top_level.txt