Metadata-Version: 1.0
Name: prygress
Version: 0.2
Summary: Threaded progress bar for running functions
Home-page: http://github.com/dboudwin/prygress
Author: Derrick Boudwin
Author-email: derrick.boudwin@gmail.com
License: MIT
Platform: UNKNOWN
